{
    "Animal": 0,
    "Box": 0,
    "Session": 1,
    "SessionType": 1,
    "SessionDuration": "2:0:0",
    "StartingTrialNumber": 10,
    "StartingBlockNumber": 1,
    "StartingTrainingLevel": 1,
    "LastTrainingLevel": 16,
    "ABLList": [
        20,
        40,
        60
    ],
    "CycleILD": true,
    "SoundIndexes": [
        2
    ],
    "Bias": 0.5,
    "MinLEDOnset": 99,
    "LEDOnsetDelta": 0.001,
    "LEDOnsetTarget": 0.2,
    "ExpLEDOnset": 0.075,
    "MinFT": 99,
    "FTDelta": 0.001,
    "FTTarget": 0.2,
    "ExpFTMean": 0.075,
    "MinRT": 0.01,
    "RTDelta": 0.001,
    "RTTarget": 0.15,
    "MaxRT": 5,
    "MaxSamplingTime": [],
    "MinMT": 0.01,
    "MinLNP": 0.01,
    "LNPDelta": 0.001,
    "LNPTarget": 0.01,
    "BaseReward": 25,
    "OptoSession": false,
    "OptoContinuous": true,
    "OptoRamp": 50,
    "OptoTime": 1,
    "OptoFrequency": 20,
    "OptoPulseDuration": 20
}